LICENSE
ez_setup.py
gherkin.py
nanothreads.py
nanotubes.py
setup.py
FibraNet.egg-info/PKG-INFO
FibraNet.egg-info/SOURCES.txt
FibraNet.egg-info/dependency_links.txt
FibraNet.egg-info/top_level.txt
eventnet/__init__.py
eventnet/_pygame.py
eventnet/baseevent.py
eventnet/driver.py
eventnet/net.py
sandbox/client.py
sandbox/server.py
