Metadata-Version: 1.0
Name: FibraNet
Version: 10
Summary: A cooperative threading and event driven framework with simple network capabilities.
Home-page: http://code.google.com/p/fibranet/
Author: Simon Wittber
Author-email: simonwittber@gmail.com
License: BSD
Platform: Any
